svgpdtools/__init__.py
svgpdtools/command.py
svgpdtools/ellipticalarc.py
svgpdtools/graphics.py
svgpdtools/pathdata.py
svgpdtools/py.typed
svgpdtools/terminal_command.py
svgpdtools/transform.py
svgpdtools/utils.py
svgpdtools/parser/__init__.py
svgpdtools-0.1.1.dist-info/LICENSE.txt
svgpdtools-0.1.1.dist-info/METADATA
svgpdtools-0.1.1.dist-info/WHEEL
svgpdtools-0.1.1.dist-info/entry_points.txt
svgpdtools-0.1.1.dist-info/top_level.txt
svgpdtools-0.1.1.dist-info/RECORD
