Metadata-Version: 2.1
Name: svgpdtools
Version: 0.1.1
Summary: Manipulate pathdata of SVG path-element.
Home-page: https://github.com/osmatsuda/svgpdtools
Author: Osamu Matsuda
Author-email: osmatsuda@gmail.com
Classifier: Development Status :: 4 - Beta
Classifier: License :: OSI Approved :: MIT License
Classifier: Operating System :: OS Independent
Classifier: Programming Language :: Python :: 3
Classifier: Intended Audience :: Developers
Classifier: Topic :: Multimedia :: Graphics :: Editors :: Vector-Based
Requires-Python: >=3.9
License-File: LICENSE.txt
Requires-Dist: mako (>=1)
